{
    "estadisticas": {
        "provincia": "LOJA",
        "sufragantes": "322968",
        "ausentismo": "82954",
        "electores": "405922"
    },
    "resultados_candidatos": [
        {
            "COD_CANDIDATO": 11000008,
            "COD_DIGNIDAD": 11,
            "NOM_CANDIDATO": "HENRY CUCALON",
            "NOM_PARTIDO": "MOVIMIENTO CONSTRUYE (25|CONSTRUYE)",
            "ORD_CANDIDATO": 0,
            "PORCENTAJE": 0.3,
            "VOTOS": 888
        },
        {
            "COD_CANDIDATO": 11000012,
            "COD_DIGNIDAD": 11,
            "NOM_CANDIDATO": "ENRIQUE GOMEZ",
            "NOM_PARTIDO": "PARTIDO SOCIEDAD UNIDA MÁS ACCIÓN, SUMA (23|SUMA)",
            "ORD_CANDIDATO": 0,
            "PORCENTAJE": 0.19,
            "VOTOS": 577
        },
        {
            "COD_CANDIDATO": 11000013,
            "COD_DIGNIDAD": 11,
            "NOM_CANDIDATO": "FRANCESCO TABACCHI",
            "NOM_PARTIDO": "MOVIMIENTO CREO, CREANDO OPORTUNIDADES (21|CREO)",
            "ORD_CANDIDATO": 0,
            "PORCENTAJE": 0.14,
            "VOTOS": 430
        },
        {
            "COD_CANDIDATO": 11000018,
            "COD_DIGNIDAD": 11,
            "NOM_CANDIDATO": "IVAN SAQUICELA",
            "NOM_PARTIDO": "MOVIMIENTO DEMOCRACIA SÍ (20|DSI)",
            "ORD_CANDIDATO": 0,
            "PORCENTAJE": 0.09,
            "VOTOS": 285
        },
        {
            "COD_CANDIDATO": 11000007,
            "COD_DIGNIDAD": 11,
            "NOM_CANDIDATO": "LEONIDAS IZA",
            "NOM_PARTIDO": "MOVIMIENTO DE UNIDAD PLURINACIONAL PACHAKUTIK (18|MUPP)",
            "ORD_CANDIDATO": 0,
            "PORCENTAJE": 3.78,
            "VOTOS": 11378
        },
        {
            "COD_CANDIDATO": 11000011,
            "COD_DIGNIDAD": 11,
            "NOM_CANDIDATO": "PEDRO GRANJA",
            "NOM_PARTIDO": "PARTIDO SOCIALISTA ECUATORIANO (17|PSE)",
            "ORD_CANDIDATO": 0,
            "PORCENTAJE": 0.53,
            "VOTOS": 1591
        },
        {
            "COD_CANDIDATO": 11000019,
            "COD_DIGNIDAD": 11,
            "NOM_CANDIDATO": "JUAN IVAN CUEVA",
            "NOM_PARTIDO": "MOVIMIENTO AMIGO, ACCIÓN MOVILIZADORA INDEPENDIENTE GENERANDO OPORTUNIDADES (16|AMIGO)",
            "ORD_CANDIDATO": 0,
            "PORCENTAJE": 0.25,
            "VOTOS": 744
        },
        {
            "COD_CANDIDATO": 11000016,
            "COD_DIGNIDAD": 11,
            "NOM_CANDIDATO": "CARLOS RABASCALL",
            "NOM_PARTIDO": "PARTIDO IZQUIERDA DEMOCRÁTICA (12|ID)",
            "ORD_CANDIDATO": 0,
            "PORCENTAJE": 0.22,
            "VOTOS": 660
        },
        {
            "COD_CANDIDATO": 11000015,
            "COD_DIGNIDAD": 11,
            "NOM_CANDIDATO": "LUIS FELIPE TILLERIA",
            "NOM_PARTIDO": "PARTIDO AVANZA (8|AVANZA)",
            "ORD_CANDIDATO": 0,
            "PORCENTAJE": 0.32,
            "VOTOS": 973
        },
        {
            "COD_CANDIDATO": 11000014,
            "COD_DIGNIDAD": 11,
            "NOM_CANDIDATO": "DANIEL NOBOA AZIN",
            "NOM_PARTIDO": "MOVIMIENTO ACCION DEMOCRATICA NACIONAL, ADN (7|ADN)",
            "ORD_CANDIDATO": 0,
            "PORCENTAJE": 55.87,
            "VOTOS": 168113
        },
        {
            "COD_CANDIDATO": 11000009,
            "COD_DIGNIDAD": 11,
            "NOM_CANDIDATO": "HENRY KRONFLE KOZHAYA",
            "NOM_PARTIDO": "PARTIDO SOCIAL CRISTIANO (6|PSC)",
            "ORD_CANDIDATO": 0,
            "PORCENTAJE": 0.33,
            "VOTOS": 997
        },
        {
            "COD_CANDIDATO": 11000022,
            "COD_DIGNIDAD": 11,
            "NOM_CANDIDATO": "LUISA GONZALEZ",
            "NOM_PARTIDO": "REVOLUCIÓN CIUDADANA - RETO (5-33|RC/RETO)",
            "ORD_CANDIDATO": 0,
            "PORCENTAJE": 33.02,
            "VOTOS": 99351
        },
        {
            "COD_CANDIDATO": 11000020,
            "COD_DIGNIDAD": 11,
            "NOM_CANDIDATO": "VICTOR ARAUS",
            "NOM_PARTIDO": "MOVIMIENTO PUEBLO IGUALDAD DEMOCRACIA \"PID\" (4|PID)",
            "ORD_CANDIDATO": 0,
            "PORCENTAJE": 0.15,
            "VOTOS": 464
        },
        {
            "COD_CANDIDATO": 11000010,
            "COD_DIGNIDAD": 11,
            "NOM_CANDIDATO": "ANDREA GONZALEZ",
            "NOM_PARTIDO": "PARTIDO SOCIEDAD PATRIÓTICA  21 DE ENERO (3|PSP)",
            "ORD_CANDIDATO": 0,
            "PORCENTAJE": 4.18,
            "VOTOS": 12572
        },
        {
            "COD_CANDIDATO": 11000021,
            "COD_DIGNIDAD": 11,
            "NOM_CANDIDATO": "JORGE ESCALA",
            "NOM_PARTIDO": "PARTIDO UNIDAD POPULAR (2|UP)",
            "ORD_CANDIDATO": 0,
            "PORCENTAJE": 0.37,
            "VOTOS": 1104
        },
        {
            "COD_CANDIDATO": 11000017,
            "COD_DIGNIDAD": 11,
            "NOM_CANDIDATO": "JIMMY JAIRALA VALLAZZA",
            "NOM_PARTIDO": "MOVIMIENTO CENTRO DEMOCRÁTICO (1|CD)",
            "ORD_CANDIDATO": 0,
            "PORCENTAJE": 0.26,
            "VOTOS": 785
        }
    ],
    "datos_votos": [
        {
            "tipo": "Votos Válidos",
            "valor": 93.22
        },
        {
            "tipo": "Votos Blancos",
            "valor": 2.01
        },
        {
            "tipo": "Votos Nulos",
            "valor": 4.77
        }
    ]
}